pokeycrawl/__init__.py
pokeycrawl/pokeycrawl.py
pokeycrawl-0.1.1a5.dist-info/DESCRIPTION.rst
pokeycrawl-0.1.1a5.dist-info/METADATA
pokeycrawl-0.1.1a5.dist-info/RECORD
pokeycrawl-0.1.1a5.dist-info/WHEEL
pokeycrawl-0.1.1a5.dist-info/metadata.json
pokeycrawl-0.1.1a5.dist-info/top_level.txt
