Metadata-Version: 2.0
Name: pokeycrawl
Version: 0.1.1a5
Summary: A python webcrawler
Home-page: https://github.com/wnormandin/pokeycrawl
Author: Bill Normandin
Author-email: bill@pokeybill.us
License: MIT
Keywords: spider crawler website indexing load-testing
Platform: UNKNOWN
Classifier: Development Status :: 3 - Alpha
Classifier: Intended Audience :: Developers
Classifier: Topic :: Internet :: WWW/HTTP :: Indexing/Search
Classifier: License :: OSI Approved :: MIT License
Classifier: Programming Language :: Python :: 2
Classifier: Programming Language :: Python :: 2.7
Requires-Dist: mechanize
